nbdirs/__init__.py
nbdirs/_modidx.py
nbdirs/atyp.py
nbdirs/cons.py
nbdirs/core.py
nbdirs/dirs.py
nbdirs/enum.py
nbdirs/meta.py
nbdirs/mixs.py
nbdirs/mxns.py
nbdirs/utils.py
nbdirs-0.0.8.dist-info/LICENSE
nbdirs-0.0.8.dist-info/METADATA
nbdirs-0.0.8.dist-info/WHEEL
nbdirs-0.0.8.dist-info/entry_points.txt
nbdirs-0.0.8.dist-info/top_level.txt
nbdirs-0.0.8.dist-info/RECORD
