Metadata-Version: 2.1
Name: nbdirs
Version: 0.0.8
Summary: utility for scaffolding nbdev projects
Home-page: https://github.com/dsm-72/nbdirs
Author: dsm-72
Author-email: sumner.magruder@yale.edu
License: Apache Software License 2.0
Keywords: nbdev jupyter notebook python nbdirs
Classifier: Development Status :: 4 - Beta
Classifier: Intended Audience :: Developers
Classifier: Natural Language :: English
Classifier: Programming Language :: Python :: 3.11
Classifier: License :: OSI Approved :: Apache Software License
Requires-Python: >=3.11
License-File: LICENSE
Requires-Dist: atyp
Requires-Dist: chck
Requires-Dist: nchr
Requires-Dist: nlit
Requires-Dist: pfmt
Requires-Dist: pstr
Requires-Dist: regsyn
Requires-Dist: idfunc
Requires-Dist: ropts
Requires-Dist: ispec
Requires-Dist: inhum
Requires-Dist: xath
Requires-Dist: urllib3
Provides-Extra: dev
